qtrlb/__init__.py
qtrlb/benchmark/RB1QB_tools.py
qtrlb/benchmark/__init__.py
qtrlb/benchmark/randomized_benchmarking.py
qtrlb/benchmark/state_tomography.py
qtrlb/benchmark/state_tomography_tools.py
qtrlb/calibration/__init__.py
qtrlb/calibration/autotune.py
qtrlb/calibration/calibration.py
qtrlb/calibration/mixer_correction.py
qtrlb/calibration/scan2d_classes.py
qtrlb/calibration/scan_classes.py
qtrlb/config/DAC_manager.py
qtrlb/config/__init__.py
qtrlb/config/config.py
qtrlb/config/data_manager.py
qtrlb/config/gate_manager.py
qtrlb/config/instrument_manager.py
qtrlb/config/process_manager.py
qtrlb/config/variable_manager.py
qtrlb/instruments/__init__.py
qtrlb/instruments/base.py
qtrlb/instruments/dsi_SG22000PRO.py
qtrlb/instruments/keysight_E5080B.py
qtrlb/instruments/keysight_N9010A.py
qtrlb/processing/__init__.py
qtrlb/processing/_gmm.py
qtrlb/processing/fitting.py
qtrlb/processing/plotting.py
qtrlb/processing/processing.py
qtrlb/projects/__init__.py
qtrlb/projects/ionization.py
qtrlb/utils/__init__.py
qtrlb/utils/dnn_utils.py
qtrlb/utils/general_utils.py
qtrlb/utils/pulses.py
qtrlb/utils/string_utils.py
qtrlb/utils/tone_utils.py
qtrlb/utils/transmon_harmonics.py
qtrlb/utils/transmon_utils.py
qtrlb/utils/units.py
qtrlb/utils/waveforms.py
qtrlb-0.2.1.dist-info/METADATA
qtrlb-0.2.1.dist-info/WHEEL
qtrlb-0.2.1.dist-info/licenses/LICENSE.txt
qtrlb-0.2.1.dist-info/RECORD
